LICENSE
MANIFEST.in
README.md
requirements.txt
setup.cfg
setup.py
resc/__init__.py
resc/__main__.py
resc/_resc.py
resc/cpu.py
resc/cron.py
resc/detect.py
resc/disk.py
resc/file.py
resc/header.py
resc/logical.py
resc/memory.py
resc/rescerr.py
resc/ssh.py
resc.egg-info/PKG-INFO
resc.egg-info/SOURCES.txt
resc.egg-info/dependency_links.txt
resc.egg-info/entry_points.txt
resc.egg-info/not-zip-safe
resc.egg-info/requires.txt
resc.egg-info/top_level.txt
resc/resclog/__init__.py
resc/resclog/anaerr.py
resc/resclog/analyze.py
resc/resclog/dump.py
resc/resclog/header.py
resc/resclog/resclog.py
resc/resclog/rformat.py
resc/resclog/cons/__init__.py
resc/resclog/cons/header.py
resc/resclog/logserver/__init__.py
resc/resclog/logserver/env.py
resc/resclog/logserver/log.py
resc/resclog/logserver/server.py
resc/resclog/logserver/__pycache__/__init__.cpython-38.pyc
resc/resclog/logserver/__pycache__/env.cpython-38.pyc
resc/resclog/logserver/__pycache__/log.cpython-38.pyc
resc/resclog/logserver/__pycache__/server.cpython-38.pyc
resc/resclog/logserver/static/html/index.html
resc/resclog/logserver/static/js/index.js
resc/resclog/logserver/static/js/actions/UploadFile.js
resc/resclog/logserver/static/js/analyze/sflag.js
resc/resclog/logserver/static/js/components/Footer.js
resc/resclog/logserver/static/js/components/Header.js
resc/resclog/logserver/static/js/components/Layout.js
resc/resclog/logserver/static/js/components/Main.js
resc/resclog/logserver/static/js/components/Header/Title.js
resc/resclog/logserver/static/js/components/Header/UploadFile.js
resc/resclog/logserver/static/js/components/Main/Analyze/Analyze.js
resc/resclog/logserver/static/js/components/Main/Analyze/Content.js
resc/resclog/logserver/static/js/components/Main/Analyze/Date.js
resc/resclog/logserver/static/js/components/Main/Analyze/Eme.js
resc/resclog/logserver/static/js/components/Main/Analyze/Normal.js
resc/resclog/logserver/static/js/components/Main/Analyze/Normal/Date.js
resc/resclog/logserver/static/js/components/Main/Analyze/Normal/File.js
resc/resclog/logserver/static/js/components/Main/Analyze/Normal/Func.js
resc/resclog/logserver/static/js/components/Main/Analyze/Normal/Over.js
