Metadata-Version: 2.1
Name: resc
Version: 0.1.0
Summary: RESC(RESource Checker)
Home-page: https://github.com/tatsuya4649/resc
Author: tatsuya.s
License: UNKNOWN
Platform: UNKNOWN
Classifier: Operating System :: POSIX :: Linux
Classifier: Operating System :: Unix
Classifier: Programming Language :: Python
Classifier: Programming Language :: Python :: 3.6
Classifier: Programming Language :: Python :: 3.7
Classifier: Programming Language :: Python :: 3.8
Classifier: Programming Language :: Python :: 3.9
Classifier: License :: OSI Approved :: MIT License
